dnn_for_kaggle/__init__.py
dnn_for_kaggle/embeddings/__init__.py
dnn_for_kaggle/embeddings/embedding_factory.py
dnn_for_kaggle/embeddings/embedding_utils.py
dnn_for_kaggle/models/__init__.py
dnn_for_kaggle/models/attention_factory.py
dnn_for_kaggle/models/base_model.py
dnn_for_kaggle/models/fttransformer.py
dnn_for_kaggle/models/mlp.py
dnn_for_kaggle/models/model_utils.py
dnn_for_kaggle-0.0.1.dist-info/METADATA
dnn_for_kaggle-0.0.1.dist-info/WHEEL
dnn_for_kaggle-0.0.1.dist-info/licenses/LICENSE
dnn_for_kaggle-0.0.1.dist-info/RECORD
