Metadata-Version: 2.4
Name: dnn_for_kaggle
Version: 0.0.1
Summary: Deep learning tools for tabular data
Project-URL: Homepage, https://github.com/AliHaiderAhmad001/dnn_for_kaggle/tree/main
Project-URL: Issues, https://github.com/AliHaiderAhmad001/dnn_for_kaggle/issues
Author-email: Ali Haidar Ahmad <ali.h.ahmad001@gmail.com>
License: <<<<<<< HEAD
License-File: LICENSE
Classifier: License :: OSI Approved :: MIT License
Classifier: Operating System :: OS Independent
Classifier: Programming Language :: Python :: 3
Requires-Python: >=3.8
